django_sass_compiler/__init__.py
django_sass_compiler/apps.py
django_sass_compiler/management/commands/sass-compiler.py
django_sass_compiler-1.1.0.dist-info/LICENSE
django_sass_compiler-1.1.0.dist-info/METADATA
django_sass_compiler-1.1.0.dist-info/WHEEL
django_sass_compiler-1.1.0.dist-info/top_level.txt
django_sass_compiler-1.1.0.dist-info/RECORD
