Metadata-Version: 2.1
Name: django-sass-compiler
Version: 1.1.0
Summary: Simplify the use of Sass in Django.
Home-page: https://github.com/jaberbu/django-sass-compiler
Author: Jacek B. Budzynski
Author-email: jacek.b.budzynski@gmail.com
License: BSD license
Platform: UNKNOWN
Classifier: Intended Audience :: Developers
Classifier: License :: OSI Approved :: BSD License
Classifier: Natural Language :: Spanish
Classifier: Natural Language :: Polish
Classifier: Programming Language :: Python :: 3
Classifier: Programming Language :: Python :: 3 :: Only
Classifier: Framework :: Django
Classifier: Framework :: Django :: 2.0
Classifier: Framework :: Django :: 3.0
Classifier: Environment :: Web Environment
Requires-Dist: django
Requires-Dist: libsass
